fast_form/__init__.py
fast_form/main.py
fast_form/config/__init__.py
fast_form/config/configuration_dataclasses.py
fast_form/config/configuration_loading.py
fast_form/field_recognizer/__init__.py
fast_form/field_recognizer/model.py
fast_form/field_recognizer/recognize_all.py
fast_form/field_recognizer/recognize_boxes.py
fast_form/field_recognizer/recognize_letters.py
fast_form/field_recognizer/recognizing_dataclasses.py
fast_form/field_recognizer/resizing_for_recognizers.py
fast_form/model_data/model_letters.h5
fast_form/model_data/model_letters.json
fast_form/model_data/model_letters_mapping.json
fast_form/model_data/model_numbers.h5
fast_form/model_data/model_numbers.json
fast_form/model_data/model_numbers_mapping.json
fast_form/outputting/__init__.py
fast_form/outputting/ouput_data.py
fast_form/outputting/process_document.py
fast_form/outputting/utils_for_main.py
fast_form/preprocessing/__init__.py
fast_form/preprocessing/image_sift.py
fast_form/preprocessing/normalization.py
fast_form/preprocessing/preprocess.py
fast_form/preprocessing/templating.py
fast_form/real_forms/PID_forms/config.json
fast_form/real_forms/PID_forms/template.pdf
fast_form/structure_parser/__init__.py
fast_form/structure_parser/form_structure_dataclasses.py
fast_form/structure_parser/page_structure_parser.py
fast_form/tests/__init__.py
fast_form/tests/test_basic_questionnaire.py
fast_form/tests/test_special_questionnaire.py
fast_form/tests/form1_for_test/config.json
fast_form/tests/form1_for_test/path_config.json
fast_form/tests/form1_for_test/template.jpg
fast_form/tests/form1_for_test/documents/document.jpg
fast_form/tests/form2_for_test/config.json
fast_form/tests/form2_for_test/path_config.json
fast_form/tests/form2_for_test/template.pdf
fast_form/tests/form2_for_test/documents/document.jpg
fast_form/utils/__init__.py
fast_form/utils/image_loading.py
notebooks/__init__.py
notebooks/utils_for_config_creation/__init__.py
notebooks/utils_for_config_creation/utils.py
fast_form-0.4.0.dist-info/LICENSE
fast_form-0.4.0.dist-info/METADATA
fast_form-0.4.0.dist-info/WHEEL
fast_form-0.4.0.dist-info/entry_points.txt
fast_form-0.4.0.dist-info/top_level.txt
fast_form-0.4.0.dist-info/RECORD
