Metadata-Version: 2.1
Name: fast-form
Version: 0.4.0
Summary: Automatically process scanned forms
Home-page: https://github.com/kubantjan/fast-form
Author: Mild Blue
Author-email: info@mild.blue
License: MIT
Keywords: form questionnaire omr
Platform: UNKNOWN
Classifier: Development Status :: 3 - Alpha
Classifier: Intended Audience :: Developers
Classifier: Topic :: Software Development :: Testing
Classifier: License :: OSI Approved :: MIT License
Classifier: Programming Language :: Python :: 3.7
Classifier: Programming Language :: Python :: 3.8
Classifier: Programming Language :: Python :: 3.9
Requires-Dist: opencv-contrib-python (>=4.4.0.42)
Requires-Dist: numpy (<=1.19.2)
Requires-Dist: h5py (<=2.10.0)
Requires-Dist: tensorflow (>=2.4.1)
Requires-Dist: pandas (>=1.1.4)
Requires-Dist: keras (>=2.4.3)
Requires-Dist: autopep8 (>=1.5.4)
Requires-Dist: dacite (>=1.5.1)
Requires-Dist: openpyxl (>=3.0.5)
Requires-Dist: pdf2image (>=1.14.0)
Requires-Dist: xlrd (>=1.2.0)
Provides-Extra: dev
Requires-Dist: matplotlib ; extra == 'dev'
Requires-Dist: ipykernel ; extra == 'dev'
Requires-Dist: pre-commit ; extra == 'dev'
